MANIFEST.in
README.md
setup.cfg
setup.py
src/thriftplus/__init__.py
src/thriftplus/package.pubspec.yaml
src/thriftplus/package.setup.py
src/thriftplus/thriftplus.py
src/thriftplus.egg-info/PKG-INFO
src/thriftplus.egg-info/SOURCES.txt
src/thriftplus.egg-info/dependency_links.txt
src/thriftplus.egg-info/entry_points.txt
src/thriftplus.egg-info/not-zip-safe
src/thriftplus.egg-info/requires.txt
src/thriftplus.egg-info/top_level.txt