Metadata-Version: 1.0
Name: thriftplus
Version: 0.0.3
Summary: A compiler for ThriftPlus, which is an extension to Thrift, with better support for emitting packages and with a niftier library and import system.
Home-page: http://github.com/silver-saas/thriftplus
Author: Horia Coman
Author-email: horia141@gmail.com
License: All right reserved
Keywords: thriftplus compiler thrift
Platform: UNKNOWN
